pydb_vj/__init__.py
pydb_vj/db_system.py
pydb_vj-0.3.7.dist-info/METADATA
pydb_vj-0.3.7.dist-info/WHEEL
pydb_vj-0.3.7.dist-info/RECORD
